{
    "edited": false,
    "votes": [
        {
            "vote": "aye",
            "member": {
                "first_name": "Deborah",
                "last_name": "O'Neill",
                "person": {
                    "id": 10747
                },
                "electorate": "NSW",
                "party": "Australian Labor Party",
                "id": 100312
            }
        },
        {
            "vote": "aye",
            "member": {
                "first_name": "Louise",
                "last_name": "Pratt",
                "person": {
                    "id": 10714
                },
                "electorate": "WA",
                "party": "Australian Labor Party",
                "id": 100259
            }
        },
        {
            "vote": "aye",
            "member": {
                "first_name": "Scott",
                "last_name": "Ludlam",
                "person": {
                    "id": 10713
                },
                "electorate": "WA",
                "party": "Australian Greens",
                "id": 100258
            }
        },
        {
            "vote": "aye",
            "member": {
                "first_name": "Sarah",
                "last_name": "Hanson-Young",
                "person": {
                    "id": 10711
                },
                "electorate": "SA",
                "party": "Australian Greens",
                "id": 100256
            }
        },
        {
            "vote": "aye",
            "member": {
                "first_name": "Mark",
                "last_name": "Furner",
                "person": {
                    "id": 10710
                },
                "electorate": "Queensland",
                "party": "Australian Labor Party",
                "id": 100255
            }
        },
        {
            "vote": "aye",
            "member": {
                "first_name": "Don",
                "last_name": "Farrell",
                "person": {
                    "id": 10708
                },
                "electorate": "SA",
                "party": "Australian Labor Party",
                "id": 100253
            }
        },
        {
            "vote": "aye",
            "member": {
                "first_name": "Doug",
                "last_name": "Cameron",
                "person": {
                    "id": 10706
                },
                "electorate": "NSW",
                "party": "Australian Labor Party",
                "id": 100251
            }
        },
        {
            "vote": "aye",
            "member": {
                "first_name": "Catryna",
                "last_name": "Bilyk",
                "person": {
                    "id": 10705
                },
                "electorate": "Tasmania",
                "party": "Australian Labor Party",
                "id": 100250
            }
        },
        {
            "vote": "aye",
            "member": {
                "first_name": "Glenn",
                "last_name": "Sterle",
                "person": {
                    "id": 10610
                },
                "electorate": "WA",
                "party": "Australian Labor Party",
                "id": 100213
            }
        },
        {
            "vote": "aye",
            "member": {
                "first_name": "Ursula",
                "last_name": "Stephens",
                "person": {
                    "id": 10609
                },
                "electorate": "NSW",
                "party": "Australian Labor Party",
                "id": 100212
            }
        },
        {
            "vote": "aye",
            "member": {
                "first_name": "John",
                "last_name": "Hogg",
                "person": {
                    "id": 10309
                },
                "electorate": "Queensland",
                "party": "PRES",
                "id": 100277
            }
        },
        {
            "vote": "aye",
            "member": {
                "first_name": "Richard",
                "last_name": "Di Natale",
                "person": {
                    "id": 10755
                },
                "electorate": "Victoria",
                "party": "Australian Greens",
                "id": 100285
            }
        },
        {
            "vote": "aye",
            "member": {
                "first_name": "Alex",
                "last_name": "Gallacher",
                "person": {
                    "id": 10757
                },
                "electorate": "SA",
                "party": "Australian Labor Party",
                "id": 100288
            }
        },
        {
            "vote": "aye",
            "member": {
                "first_name": "Nova",
                "last_name": "Peris",
                "person": {
                    "id": 10820
                },
                "electorate": "NT",
                "party": "Australian Labor Party",
                "id": 100309
            }
        },
        {
            "vote": "aye",
            "member": {
                "first_name": "Sam",
                "last_name": "Dastyari",
                "person": {
                    "id": 10819
                },
                "electorate": "NSW",
                "party": "Australian Labor Party",
                "id": 100308
            }
        },
        {
            "vote": "aye",
            "member": {
                "first_name": "Sue",
                "last_name": "Lines",
                "person": {
                    "id": 10782
                },
                "electorate": "WA",
                "party": "Australian Labor Party",
                "id": 100307
            }
        },
        {
            "vote": "aye",
            "member": {
                "first_name": "Lin",
                "last_name": "Thorp",
                "person": {
                    "id": 10769
                },
                "electorate": "Tasmania",
                "party": "Australian Labor Party",
                "id": 100304
            }
        },
        {
            "vote": "aye",
            "member": {
                "first_name": "Penny",
                "last_name": "Wright",
                "person": {
                    "id": 10765
                },
                "electorate": "SA",
                "party": "Australian Greens",
                "id": 100300
            }
        },
        {
            "vote": "aye",
            "member": {
                "first_name": "Larissa",
                "last_name": "Waters",
                "person": {
                    "id": 10764
                },
                "electorate": "Queensland",
                "party": "Australian Greens",
                "id": 100298
            }
        },
        {
            "vote": "aye",
            "member": {
                "first_name": "Anne",
                "last_name": "Urquhart",
                "person": {
                    "id": 10763
                },
                "electorate": "Tasmania",
                "party": "Australian Labor Party",
                "id": 100297
            }
        },
        {
            "vote": "aye",
            "member": {
                "first_name": "Lisa",
                "last_name": "Singh",
                "person": {
                    "id": 10761
                },
                "electorate": "Tasmania",
                "party": "Australian Labor Party",
                "id": 100295
            }
        },
        {
            "vote": "aye",
            "member": {
                "first_name": "Lee",
                "last_name": "Rhiannon",
                "person": {
                    "id": 10760
                },
                "electorate": "NSW",
                "party": "Australian Greens",
                "id": 100293
            }
        },
        {
            "vote": "aye",
            "member": {
                "first_name": "Rachel",
                "last_name": "Siewert",
                "person": {
                    "id": 10584
                },
                "electorate": "WA",
                "party": "Australian Greens",
                "id": 100208
            }
        },
        {
            "vote": "aye",
            "member": {
                "first_name": "Jacinta",
                "last_name": "Collins",
                "person": {
                    "id": 10135
                },
                "electorate": "Victoria",
                "party": "Australian Labor Party",
                "id": 100265
            }
        },
        {
            "vote": "aye",
            "member": {
                "first_name": "Helen",
                "last_name": "Polley",
                "person": {
                    "id": 10515
                },
                "electorate": "Tasmania",
                "party": "Australian Labor Party",
                "id": 100178
            }
        },
        {
            "vote": "aye",
            "member": {
                "first_name": "Kate",
                "last_name": "Lundy",
                "person": {
                    "id": 10398
                },
                "electorate": "ACT",
                "party": "Australian Labor Party",
                "id": 100129
            }
        },
        {
            "vote": "aye",
            "member": {
                "first_name": "Joe",
                "last_name": "Ludwig",
                "person": {
                    "id": 10397
                },
                "electorate": "Queensland",
                "party": "Australian Labor Party",
                "id": 100128
            }
        },
        {
            "vote": "aye",
            "member": {
                "first_name": "Anne",
                "last_name": "McEwen",
                "person": {
                    "id": 10433
                },
                "electorate": "SA",
                "party": "Australian Labor Party",
                "id": 100145
            }
        },
        {
            "vote": "aye",
            "member": {
                "first_name": "Jan",
                "last_name": "McLucas",
                "person": {
                    "id": 10447
                },
                "electorate": "Queensland",
                "party": "Australian Labor Party",
                "id": 100152
            }
        },
        {
            "vote": "aye",
            "member": {
                "first_name": "Kim",
                "last_name": "Carr",
                "person": {
                    "id": 10103
                },
                "electorate": "Victoria",
                "party": "Australian Labor Party",
                "id": 100036
            }
        },
        {
            "vote": "aye",
            "member": {
                "first_name": "Christine",
                "last_name": "Milne",
                "person": {
                    "id": 10458
                },
                "electorate": "Tasmania",
                "party": "Australian Greens",
                "id": 100156
            }
        },
        {
            "vote": "aye",
            "member": {
                "first_name": "Claire",
                "last_name": "Moore",
                "person": {
                    "id": 10463
                },
                "electorate": "Queensland",
                "party": "Australian Labor Party",
                "id": 100159
            }
        },
        {
            "vote": "aye",
            "member": {
                "first_name": "Stephen",
                "last_name": "Conroy",
                "person": {
                    "id": 10142
                },
                "electorate": "Victoria",
                "party": "Australian Labor Party",
                "id": 100053
            }
        },
        {
            "vote": "aye",
            "member": {
                "first_name": "Peter",
                "last_name": "Whish-Wilson",
                "person": {
                    "id": 10780
                },
                "electorate": "Tasmania",
                "party": "Australian Greens",
                "id": 100305
            }
        },
        {
            "vote": "aye",
            "member": {
                "first_name": "Carol",
                "last_name": "Brown",
                "person": {
                    "id": 10071
                },
                "electorate": "Tasmania",
                "party": "Australian Labor Party",
                "id": 100026
            }
        },
        {
            "vote": "no",
            "member": {
                "first_name": "Arthur",
                "last_name": "Sinodinos",
                "person": {
                    "id": 10766
                },
                "electorate": "NSW",
                "party": "Liberal Party",
                "id": 100301
            }
        },
        {
            "vote": "no",
            "member": {
                "first_name": "Dean",
                "last_name": "Smith",
                "person": {
                    "id": 10768
                },
                "electorate": "WA",
                "party": "Liberal Party",
                "id": 100303
            }
        },
        {
            "vote": "no",
            "member": {
                "first_name": "Alan",
                "last_name": "Eggleston",
                "person": {
                    "id": 10193
                },
                "electorate": "WA",
                "party": "Liberal Party",
                "id": 100071
            }
        },
        {
            "vote": "no",
            "member": {
                "first_name": "Anne",
                "last_name": "Ruston",
                "person": {
                    "id": 10781
                },
                "electorate": "SA",
                "party": "Liberal Party",
                "id": 100306
            }
        },
        {
            "vote": "no",
            "member": {
                "first_name": "George",
                "last_name": "Brandis",
                "person": {
                    "id": 10067
                },
                "electorate": "Queensland",
                "party": "Liberal Party",
                "id": 100025
            }
        },
        {
            "vote": "no",
            "member": {
                "first_name": "Sue",
                "last_name": "Boyce",
                "person": {
                    "id": 10062
                },
                "electorate": "Queensland",
                "party": "Liberal Party",
                "id": 100024
            }
        },
        {
            "vote": "no",
            "member": {
                "first_name": "Ron",
                "last_name": "Boswell",
                "person": {
                    "id": 10057
                },
                "electorate": "Queensland",
                "party": "National Party",
                "id": 100022
            }
        },
        {
            "vote": "no",
            "member": {
                "first_name": "Zed",
                "last_name": "Seselja",
                "person": {
                    "id": 10822
                },
                "electorate": "ACT",
                "party": "Liberal Party",
                "id": 100311
            }
        },
        {
            "vote": "no",
            "member": {
                "first_name": "Cory",
                "last_name": "Bernardi",
                "person": {
                    "id": 10038
                },
                "electorate": "SA",
                "party": "Liberal Party",
                "id": 100013
            }
        },
        {
            "vote": "no",
            "member": {
                "first_name": "Concetta",
                "last_name": "Fierravanti-Wells",
                "person": {
                    "id": 10222
                },
                "electorate": "NSW",
                "party": "Liberal Party",
                "id": 100082
            }
        },
        {
            "vote": "no",
            "member": {
                "first_name": "Mitch",
                "last_name": "Fifield",
                "person": {
                    "id": 10224
                },
                "electorate": "Victoria",
                "party": "Liberal Party",
                "id": 100083
            }
        },
        {
            "vote": "no",
            "member": {
                "first_name": "Bridget",
                "last_name": "McKenzie",
                "person": {
                    "id": 10758
                },
                "electorate": "Victoria",
                "party": "National Party",
                "id": 100291
            }
        },
        {
            "vote": "no",
            "member": {
                "first_name": "Marise",
                "last_name": "Payne",
                "person": {
                    "id": 10509
                },
                "electorate": "NSW",
                "party": "Liberal Party",
                "id": 100177
            }
        },
        {
            "vote": "no",
            "member": {
                "first_name": "Fiona",
                "last_name": "Nash",
                "person": {
                    "id": 10478
                },
                "electorate": "NSW",
                "party": "National Party",
                "id": 100164
            }
        },
        {
            "vote": "no",
            "member": {
                "first_name": "Michaelia",
                "last_name": "Cash",
                "person": {
                    "id": 10707
                },
                "electorate": "WA",
                "party": "Liberal Party",
                "id": 100252
            }
        },
        {
            "vote": "no",
            "member": {
                "first_name": "Brett",
                "last_name": "Mason",
                "person": {
                    "id": 10423
                },
                "electorate": "Queensland",
                "party": "Liberal Party",
                "id": 100140
            }
        },
        {
            "vote": "no",
            "member": {
                "first_name": "Helen",
                "last_name": "Kroger",
                "person": {
                    "id": 10712
                },
                "electorate": "Victoria",
                "party": "Liberal Party",
                "id": 100257
            }
        },
        {
            "vote": "no",
            "member": {
                "first_name": "Ian",
                "last_name": "Macdonald",
                "person": {
                    "id": 10401
                },
                "electorate": "Queensland",
                "party": "Liberal Party",
                "id": 100130
            }
        },
        {
            "vote": "no",
            "member": {
                "first_name": "John",
                "last_name": "Williams",
                "person": {
                    "id": 10716
                },
                "electorate": "NSW",
                "party": "National Party",
                "id": 100261
            }
        },
        {
            "vote": "no",
            "member": {
                "first_name": "Nigel",
                "last_name": "Scullion",
                "person": {
                    "id": 10569
                },
                "electorate": "NT",
                "party": "Country Liberal Party",
                "id": 100199
            }
        },
        {
            "vote": "no",
            "member": {
                "first_name": "Christopher",
                "last_name": "Back",
                "person": {
                    "id": 10722
                },
                "electorate": "WA",
                "party": "Liberal Party",
                "id": 100279
            }
        },
        {
            "vote": "no",
            "member": {
                "first_name": "David",
                "last_name": "Johnston",
                "person": {
                    "id": 10344
                },
                "electorate": "WA",
                "party": "Liberal Party",
                "id": 100112
            }
        },
        {
            "vote": "no",
            "member": {
                "first_name": "Sean",
                "last_name": "Edwards",
                "person": {
                    "id": 10756
                },
                "electorate": "SA",
                "party": "Liberal Party",
                "id": 100286
            }
        },
        {
            "vote": "no",
            "member": {
                "first_name": "David",
                "last_name": "Fawcett",
                "person": {
                    "id": 10215
                },
                "electorate": "SA",
                "party": "Liberal Party",
                "id": 100287
            }
        },
        {
            "vote": "no",
            "member": {
                "first_name": "Bill",
                "last_name": "Heffernan",
                "person": {
                    "id": 10296
                },
                "electorate": "NSW",
                "party": "Liberal Party",
                "id": 100101
            }
        },
        {
            "vote": "no",
            "member": {
                "first_name": "Stephen",
                "last_name": "Parry",
                "person": {
                    "id": 10507
                },
                "electorate": "Tasmania",
                "party": "DPRES",
                "id": 100840
            }
        }
    ],
    "policy_divisions": [],
    "name": "Motions \u2014 Asylum Seekers",
    "house": "senate",
    "rebellions": 0,
    "number": 1,
    "bills": [],
    "summary": "Anne McEwen\n\nAt the request of Senator Carr, I move:\n\nThat there be laid on the table by the Minister representing the Minister for Immigration and Border Protection, no later than noon on Thursday, 13 February 2014, documents detailing the number and cost of the lifeboats purchased by the Australian Government for use in border protection operations, including the cost of any upgrades or alterations; the number of lifeboats remaining in the Australian Government's possession; and details of the procurement process for these lifeboats in accordance with the Commonwealth Procurement Rules.\n\nMichaelia Cash\n\nMr Deputy President, I seek leave to make a short statement.\n\nStephen Parry\n\nLeave is granted for one minute.\n\nMichaelia Cash\n\nThe government will not be supporting this motion. The communication protocols around Operation Sovereign Borders have been made clear by this government and are working. As I confirmed yesterday in the Senate, there has not been a successful people-smuggling venture to Australia by boat since 19 December 2013.\n\nWe know that the people smugglers are looking to obtain any information that will assist them in selling their product to potential customers. This government will not support them in this endeavour. I would implore those opposite to understand and support this approach, to recognise the significant success we are having in destroying the people smugglers' business model and to recognise the lives that are being saved as a result.\n\nAfter five years of chaos on our borders, Australians voted for a better way. The Australian people have spoken very clearly on an issue that dominated the last federal election. As a government, we are delivering on our promise.\n\nJohn Hogg\n\nThe question is that general business notice of motion No. 109 moved by Senator McEwen on behalf of Senator Carr be agreed to.\n\n_Senator _ _Mark Bishop_ _ did not vote, to compensate for the vacancy caused by the resignation of Senator Joyce._\n\n",
    "aye_votes": 35,
    "date": "2014-02-12",
    "possible_turnout": 76,
    "clock_time": "3:53 PM",
    "id": 3153,
    "no_votes": 26
}